{"brand": {"relevancia": 10, "frequencia": 13}, "vinganc": {"relevancia": 10, "frequencia": 3}, "flamej": {"relevancia": 10, "frequencia": 1}, "mag": {"relevancia": 5, "frequencia": 7}, "labared": {"relevancia": 1, "frequencia": 3}, "habil": {"relevancia": 1, "frequencia": 3}, "deix": {"relevancia": 1, "frequencia": 1}, "alvos": {"relevancia": 1, "frequencia": 1}, "incandescent": {"relevancia": 1, "frequencia": 6}, "caus": {"relevancia": 1, "frequencia": 7}, "dan": {"relevancia": 1, "frequencia": 7}, "long": {"relevancia": 1, "frequencia": 1}, "acumul": {"relevancia": 1, "frequencia": 3}, "vez": {"relevancia": 1, "frequencia": 8}, "abat": {"relevancia": 1, "frequencia": 1}, "inimig": {"relevancia": 1, "frequencia": 5}, "recup": {"relevancia": 1, "frequencia": 1}, "man": {"relevancia": 1, "frequencia": 1}, "cheg": {"relevancia": 1, "frequencia": 2}, "maxim": {"relevancia": 1, "frequencia": 2}, "campea": {"relevancia": 1, "frequencia": 1}, "monstr": {"relevancia": 1, "frequencia": 1}, "grand": {"relevancia": 1, "frequencia": 1}, "torn": {"relevancia": 1, "frequencia": 1}, "instavel": {"relevancia": 1, "frequencia": 1}, "deton": {"relevancia": 1, "frequencia": 1}, "aplic": {"relevancia": 1, "frequencia": 1}, "efeit": {"relevancia": 1, "frequencia": 1}, "are": {"relevancia": 1, "frequencia": 3}, "redor": {"relevancia": 1, "frequencia": 1}, "vitim": {"relevancia": 1, "frequencia": 1}, "cauteriz": {"relevancia": 1, "frequencia": 2}, "lanc": {"relevancia": 1, "frequencia": 2}, "bol": {"relevancia": 1, "frequencia": 1}, "fog": {"relevancia": 1, "frequencia": 4}, "magic": {"relevancia": 1, "frequencia": 5}, "alvo": {"relevancia": 1, "frequencia": 5}, "atordo": {"relevancia": 1, "frequencia": 1}, "1,5s": {"relevancia": 1, "frequencia": 1}, "pil": {"relevancia": 1, "frequencia": 2}, "cham": {"relevancia": 1, "frequencia": 9}, "apos": {"relevancia": 1, "frequencia": 3}, "curt": {"relevancia": 1, "frequencia": 1}, "interval": {"relevancia": 1, "frequencia": 1}, "cri": {"relevancia": 1, "frequencia": 1}, "unidad": {"relevancia": 1, "frequencia": 2}, "sofr": {"relevancia": 1, "frequencia": 2}, "adicional": {"relevancia": 1, "frequencia": 1}, "conflagr": {"relevancia": 1, "frequencia": 2}, "conjur": {"relevancia": 1, "frequencia": 1}, "poder": {"relevancia": 1, "frequencia": 1}, "explosa": {"relevancia": 1, "frequencia": 1}, "espalh": {"relevancia": 1, "frequencia": 2}, "prox": {"relevancia": 1, "frequencia": 2}, "alcanc": {"relevancia": 1, "frequencia": 1}, "dobr": {"relevancia": 1, "frequencia": 1}, "piroclasm": {"relevancia": 1, "frequencia": 2}, "desfer": {"relevancia": 1, "frequencia": 1}, "devast": {"relevancia": 1, "frequencia": 1}, "torrent": {"relevancia": 1, "frequencia": 1}, "ressalt": {"relevancia": 1, "frequencia": 3}, "indo": {"relevancia": 1, "frequencia": 2}, "cad": {"relevancia": 1, "frequencia": 1}, "prioriz": {"relevancia": 1, "frequencia": 1}, "campeo": {"relevancia": 1, "frequencia": 1}, "brev": {"relevancia": 1, "frequencia": 1}, "lentida": {"relevancia": 1, "frequencia": 1}, "criatur": {"relevancia": 1, "frequencia": 2}, "conhec": {"relevancia": 1, "frequencia": 2}, "kegan": {"relevancia": 1, "frequencia": 13}, "rodh": {"relevancia": 1, "frequencia": 2}, "membr": {"relevancia": 1, "frequencia": 1}, "gel": {"relevancia": 1, "frequencia": 3}, "freljord": {"relevancia": 1, "frequencia": 4}, "hoj": {"relevancia": 1, "frequencia": 2}, "lica": {"relevancia": 1, "frequencia": 1}, "tentaca": {"relevancia": 1, "frequencia": 2}, "pod": {"relevancia": 1, "frequencia": 7}, "maior": {"relevancia": 1, "frequencia": 1}, "faz": {"relevancia": 1, "frequencia": 1}, "enquant": {"relevancia": 1, "frequencia": 4}, "busc": {"relevancia": 1, "frequencia": 4}, "lendar": {"relevancia": 1, "frequencia": 2}, "run": {"relevancia": 1, "frequencia": 6}, "glob": {"relevancia": 1, "frequencia": 2}, "tra": {"relevancia": 1, "frequencia": 1}, "companheir": {"relevancia": 1, "frequencia": 1}, "peg": {"relevancia": 1, "frequencia": 1}, "instant": {"relevancia": 1, "frequencia": 1}, "hom": {"relevancia": 1, "frequencia": 1}, "exist": {"relevancia": 1, "frequencia": 1}, "alma": {"relevancia": 1, "frequencia": 2}, "consum": {"relevancia": 1, "frequencia": 3}, "corp": {"relevancia": 1, "frequencia": 3}, "involucr": {"relevancia": 1, "frequencia": 1}, "viv": {"relevancia": 1, "frequencia": 1}, "agor": {"relevancia": 1, "frequencia": 1}, "vag": {"relevancia": 1, "frequencia": 1}, "valoran": {"relevancia": 1, "frequencia": 1}, "outr": {"relevancia": 1, "frequencia": 4}, "jur": {"relevancia": 1, "frequencia": 1}, "erros": {"relevancia": 1, "frequencia": 1}, "nunc": {"relevancia": 1, "frequencia": 1}, "ter": {"relevancia": 1, "frequencia": 1}, "duz": {"relevancia": 1, "frequencia": 1}, "vid": {"relevancia": 1, "frequencia": 2}, "mort": {"relevancia": 1, "frequencia": 4}, "filh": {"relevancia": 1, "frequencia": 2}, "curandeir": {"relevancia": 1, "frequencia": 1}, "vist": {"relevancia": 1, "frequencia": 1}, "forasteir": {"relevancia": 1, "frequencia": 2}, "desd": {"relevancia": 1, "frequencia": 1}, "nasciment": {"relevancia": 1, "frequencia": 1}, "pequen": {"relevancia": 1, "frequencia": 3}, "oficin": {"relevancia": 1, "frequencia": 1}, "herb": {"relevancia": 1, "frequencia": 1}, "ma": {"relevancia": 1, "frequencia": 3}, "permit": {"relevancia": 1, "frequencia": 2}, "ambos": {"relevancia": 1, "frequencia": 1}, "sobreviv": {"relevancia": 1, "frequencia": 1}, "marg": {"relevancia": 1, "frequencia": 1}, "comun": {"relevancia": 1, "frequencia": 1}, "costeir": {"relevancia": 1, "frequencia": 1}, "canal": {"relevancia": 1, "frequencia": 1}, "rygann": {"relevancia": 1, "frequencia": 1}, "visit": {"relevancia": 1, "frequencia": 1}, "amig": {"relevancia": 1, "frequencia": 3}, "frequent": {"relevancia": 1, "frequencia": 2}, "aind": {"relevancia": 1, "frequencia": 1}, "sab": {"relevancia": 1, "frequencia": 3}, "pai": {"relevancia": 1, "frequencia": 2}, "hav": {"relevancia": 1, "frequencia": 5}, "sid": {"relevancia": 1, "frequencia": 1}, "rapin": {"relevancia": 1, "frequencia": 2}, "result": {"relevancia": 1, "frequencia": 1}, "motiv": {"relevancia": 1, "frequencia": 1}, "ostrac": {"relevancia": 1, "frequencia": 1}, "aldeo": {"relevancia": 1, "frequencia": 1}, "bastard": {"relevancia": 1, "frequencia": 1}, "solida": {"relevancia": 1, "frequencia": 1}, "ressent": {"relevancia": 1, "frequencia": 1}, "cresc": {"relevancia": 1, "frequencia": 1}, "dentr": {"relevancia": 1, "frequencia": 1}, "muit": {"relevancia": 1, "frequencia": 3}, "manifest": {"relevancia": 1, "frequencia": 1}, "form": {"relevancia": 1, "frequencia": 1}, "violent": {"relevancia": 1, "frequencia": 1}, "anos": {"relevancia": 1, "frequencia": 1}, "invern": {"relevancia": 1, "frequencia": 1}, "aparent": {"relevancia": 1, "frequencia": 1}, "intermin": {"relevancia": 1, "frequencia": 1}, "fragil": {"relevancia": 1, "frequencia": 1}, "enfim": {"relevancia": 1, "frequencia": 1}, "ced": {"relevancia": 1, "frequencia": 1}, "cinz": {"relevancia": 1, "frequencia": 1}, "comec": {"relevancia": 1, "frequencia": 1}, "pens": {"relevancia": 1, "frequencia": 1}, "pesso": {"relevancia": 1, "frequencia": 1}, "pass": {"relevancia": 1, "frequencia": 2}, "cur": {"relevancia": 1, "frequencia": 2}, "nenhum": {"relevancia": 1, "frequencia": 1}, "ido": {"relevancia": 1, "frequencia": 1}, "lament": {"relevancia": 1, "frequencia": 1}, "fund": {"relevancia": 1, "frequencia": 2}, "quer": {"relevancia": 1, "frequencia": 1}, "simples": {"relevancia": 1, "frequencia": 1}, "desaparec": {"relevancia": 1, "frequencia": 1}, "cumpr": {"relevancia": 1, "frequencia": 1}, "vontad": {"relevancia": 1, "frequencia": 1}, "antes": {"relevancia": 1, "frequencia": 2}, "execut": {"relevancia": 1, "frequencia": 1}, "incendi": {"relevancia": 1, "frequencia": 1}, "alde": {"relevancia": 1, "frequencia": 1}, "fug": {"relevancia": 1, "frequencia": 1}, "mei": {"relevancia": 1, "frequencia": 1}, "escurida": {"relevancia": 1, "frequencia": 1}, "noit": {"relevancia": 1, "frequencia": 1}, "lev": {"relevancia": 1, "frequencia": 3}, "consig": {"relevancia": 1, "frequencia": 1}, "cicatriz": {"relevancia": 1, "frequencia": 1}, "jam": {"relevancia": 1, "frequencia": 1}, "percorr": {"relevancia": 1, "frequencia": 1}, "tundr": {"relevancia": 1, "frequencia": 1}, "diz": {"relevancia": 1, "frequencia": 1}, "procur": {"relevancia": 1, "frequencia": 1}, "...": {"relevancia": 1, "frequencia": 2}, "men": {"relevancia": 1, "frequencia": 1}, "rost": {"relevancia": 1, "frequencia": 1}, "gentil": {"relevancia": 1, "frequencia": 1}, "mostr": {"relevancia": 1, "frequencia": 1}, "futil": {"relevancia": 1, "frequencia": 1}, "escond": {"relevancia": 1, "frequencia": 2}, "cavern": {"relevancia": 1, "frequencia": 1}, "esper": {"relevancia": 1, "frequencia": 2}, "entant": {"relevancia": 1, "frequencia": 1}, "misteri": {"relevancia": 1, "frequencia": 1}, "ryze": {"relevancia": 1, "frequencia": 6}, "viu": {"relevancia": 1, "frequencia": 1}, "potencial": {"relevancia": 1, "frequencia": 1}, "naquel": {"relevancia": 1, "frequencia": 2}, "jov": {"relevancia": 1, "frequencia": 2}, "semi-congel": {"relevancia": 1, "frequencia": 1}, "adot": {"relevancia": 1, "frequencia": 2}, "aprendiz": {"relevancia": 1, "frequencia": 3}, "tant": {"relevancia": 1, "frequencia": 2}, "instrutor": {"relevancia": 1, "frequencia": 1}, "quant": {"relevancia": 1, "frequencia": 1}, "frustraco": {"relevancia": 1, "frequencia": 1}, "desenvolv": {"relevancia": 1, "frequencia": 1}, "nov": {"relevancia": 1, "frequencia": 1}, "ignor": {"relevancia": 1, "frequencia": 1}, "ped": {"relevancia": 1, "frequencia": 1}, "humildad": {"relevancia": 1, "frequencia": 1}, "pacienc": {"relevancia": 1, "frequencia": 1}, "durant": {"relevancia": 1, "frequencia": 1}, "treinament": {"relevancia": 1, "frequencia": 1}, "infeliz": {"relevancia": 1, "frequencia": 2}, "instru": {"relevancia": 1, "frequencia": 1}, "sempr": {"relevancia": 1, "frequencia": 2}, "secundari": {"relevancia": 1, "frequencia": 1}, "relaca": {"relevancia": 1, "frequencia": 1}, "missa": {"relevancia": 1, "frequencia": 1}, "original": {"relevancia": 1, "frequencia": 1}, "desej": {"relevancia": 1, "frequencia": 1}, "encontr": {"relevancia": 1, "frequencia": 2}, "signific": {"relevancia": 1, "frequencia": 1}, "ruin": {"relevancia": 1, "frequencia": 1}, "runeterr": {"relevancia": 1, "frequencia": 2}, "achar": {"relevancia": 1, "frequencia": 1}, "dess": {"relevancia": 1, "frequencia": 1}, "fragment": {"relevancia": 1, "frequencia": 1}, "enfrent": {"relevancia": 1, "frequencia": 1}, "mesm": {"relevancia": 1, "frequencia": 1}, "desesper": {"relevancia": 1, "frequencia": 1}, "enlouquec": {"relevancia": 1, "frequencia": 1}, "font": {"relevancia": 1, "frequencia": 1}, "tod": {"relevancia": 1, "frequencia": 2}, "mund": {"relevancia": 1, "frequencia": 2}, "contr": {"relevancia": 1, "frequencia": 1}, "advertent": {"relevancia": 1, "frequencia": 1}, "mestr": {"relevancia": 1, "frequencia": 2}, "escolh": {"relevancia": 1, "frequencia": 1}, "tom": {"relevancia": 1, "frequencia": 1}, "imens": {"relevancia": 1, "frequencia": 1}, "observ": {"relevancia": 1, "frequencia": 1}, "impotent": {"relevancia": 1, "frequencia": 1}, "pur": {"relevancia": 1, "frequencia": 1}, "nasc": {"relevancia": 1, "frequencia": 1}, "moment": {"relevancia": 1, "frequencia": 1}, "resgat": {"relevancia": 1, "frequencia": 1}, "nev": {"relevancia": 1, "frequencia": 1}, "diss": {"relevancia": 1, "frequencia": 1}, "lug": {"relevancia": 1, "frequencia": 1}, "ser": {"relevancia": 1, "frequencia": 2}, "vingat": {"relevancia": 1, "frequencia": 1}, "mold": {"relevancia": 1, "frequencia": 1}, "fur": {"relevancia": 1, "frequencia": 1}, "dia": {"relevancia": 1, "frequencia": 1}, "rein": {"relevancia": 1, "frequencia": 1}, "amaldico": {"relevancia": 1, "frequencia": 1}, "antig": {"relevancia": 1, "frequencia": 1}, "coloc": {"relevancia": 1, "frequencia": 1}, "qua": {"relevancia": 1, "frequencia": 1}, "quas": {"relevancia": 1, "frequencia": 1}, "escap": {"relevancia": 1, "frequencia": 1}, "secul": {"relevancia": 1, "frequencia": 1}, "existent": {"relevancia": 1, "frequencia": 1}, "anarqu": {"relevancia": 1, "frequencia": 1}, "selvag": {"relevancia": 1, "frequencia": 1}, "volt": {"relevancia": 1, "frequencia": 1}, "tud": {"relevancia": 1, "frequencia": 1}, "cruz": {"relevancia": 1, "frequencia": 1}, "ceus": {"relevancia": 1, "frequencia": 1}, "comet": {"relevancia": 1, "frequencia": 1}, "afund": {"relevancia": 1, "frequencia": 1}, "terr": {"relevancia": 1, "frequencia": 1}, "dorm": {"relevancia": 1, "frequencia": 1}, "pacif": {"relevancia": 1, "frequencia": 1}, "inconfund": {"relevancia": 1, "frequencia": 1}, "arom": {"relevancia": 1, "frequencia": 1}, "global": {"relevancia": 1, "frequencia": 1}, "pouc": {"relevancia": 1, "frequencia": 1}, "capaz": {"relevancia": 1, "frequencia": 1}, "impedi-l": {"relevancia": 1, "frequencia": 1}}