{"cork": {"relevancia": 10, "frequencia": 14}, "bombardeir": {"relevancia": 10, "frequencia": 2}, "ous": {"relevancia": 10, "frequencia": 2}, "atir": {"relevancia": 5, "frequencia": 1}, "munica": {"relevancia": 1, "frequencia": 1}, "hextec": {"relevancia": 1, "frequencia": 1}, "porcentag": {"relevancia": 1, "frequencia": 1}, "dan": {"relevancia": 1, "frequencia": 7}, "ataqu": {"relevancia": 1, "frequencia": 3}, "basic": {"relevancia": 1, "frequencia": 1}, "convert": {"relevancia": 1, "frequencia": 1}, "magic": {"relevancia": 1, "frequencia": 3}, "pod": {"relevancia": 1, "frequencia": 1}, "busc": {"relevancia": 1, "frequencia": 1}, "pacot": {"relevancia": 1, "frequencia": 1}, "bas": {"relevancia": 1, "frequencia": 1}, "conced": {"relevancia": 1, "frequencia": 1}, "veloc": {"relevancia": 1, "frequencia": 1}, "moviment": {"relevancia": 1, "frequencia": 1}, "fortalec": {"relevancia": 1, "frequencia": 1}, "conjur": {"relevancia": 1, "frequencia": 1}, "valquir": {"relevancia": 1, "frequencia": 2}, "bomb": {"relevancia": 1, "frequencia": 3}, "fosfor": {"relevancia": 1, "frequencia": 1}, "disp": {"relevancia": 1, "frequencia": 3}, "lumin": {"relevancia": 1, "frequencia": 1}, "local": {"relevancia": 1, "frequencia": 2}, "alvo": {"relevancia": 1, "frequencia": 2}, "caus": {"relevancia": 1, "frequencia": 5}, "inimig": {"relevancia": 1, "frequencia": 5}, "are": {"relevancia": 1, "frequencia": 5}, "revel": {"relevancia": 1, "frequencia": 1}, "unidad": {"relevancia": 1, "frequencia": 1}, "curt": {"relevancia": 1, "frequencia": 2}, "duraca": {"relevancia": 1, "frequencia": 1}, "sobrevo": {"relevancia": 1, "frequencia": 1}, "distanc": {"relevancia": 1, "frequencia": 1}, "solt": {"relevancia": 1, "frequencia": 1}, "cri": {"relevancia": 1, "frequencia": 1}, "rastr": {"relevancia": 1, "frequencia": 1}, "fog": {"relevancia": 1, "frequencia": 3}, "oponent": {"relevancia": 1, "frequencia": 1}, "nel": {"relevancia": 1, "frequencia": 1}, "permanec": {"relevancia": 1, "frequencia": 1}, "metralh": {"relevancia": 1, "frequencia": 2}, "rapid": {"relevancia": 1, "frequencia": 1}, "con": {"relevancia": 1, "frequencia": 1}, "frent": {"relevancia": 1, "frequencia": 2}, "reduz": {"relevancia": 1, "frequencia": 1}, "armadur": {"relevancia": 1, "frequencia": 1}, "resistent": {"relevancia": 1, "frequencia": 1}, "barrag": {"relevancia": 1, "frequencia": 2}, "miss": {"relevancia": 1, "frequencia": 3}, "missil": {"relevancia": 1, "frequencia": 2}, "direca": {"relevancia": 1, "frequencia": 1}, "explod": {"relevancia": 1, "frequencia": 1}, "impact": {"relevancia": 1, "frequencia": 1}, "armazen": {"relevancia": 1, "frequencia": 2}, "long": {"relevancia": 1, "frequencia": 1}, "temp": {"relevancia": 1, "frequencia": 2}, "limit": {"relevancia": 1, "frequencia": 1}, "maxim": {"relevancia": 1, "frequencia": 1}, "granda": {"relevancia": 1, "frequencia": 1}, "adicional": {"relevancia": 1, "frequencia": 1}, "pilot": {"relevancia": 1, "frequencia": 3}, "yordl": {"relevancia": 1, "frequencia": 3}, "ama": {"relevancia": 1, "frequencia": 1}, "duas": {"relevancia": 1, "frequencia": 1}, "cois": {"relevancia": 1, "frequencia": 2}, "acim": {"relevancia": 1, "frequencia": 1}, "qualqu": {"relevancia": 1, "frequencia": 1}, "outr": {"relevancia": 1, "frequencia": 1}, "voar": {"relevancia": 1, "frequencia": 1}, "glamor": {"relevancia": 1, "frequencia": 1}, "bigod": {"relevancia": 1, "frequencia": 1}, "...": {"relevancia": 1, "frequencia": 1}, "necessari": {"relevancia": 1, "frequencia": 1}, "ness": {"relevancia": 1, "frequencia": 1}, "ordem": {"relevancia": 1, "frequencia": 1}, "deix": {"relevancia": 1, "frequencia": 1}, "bandopol": {"relevancia": 1, "frequencia": 2}, "estabelec": {"relevancia": 1, "frequencia": 1}, "piltov": {"relevancia": 1, "frequencia": 2}, "apaixon": {"relevancia": 1, "frequencia": 1}, "maquin": {"relevancia": 1, "frequencia": 1}, "maravilh": {"relevancia": 1, "frequencia": 1}, "encontr": {"relevancia": 1, "frequencia": 2}, "dedic": {"relevancia": 1, "frequencia": 1}, "desenvolv": {"relevancia": 1, "frequencia": 1}, "engenhoc": {"relevancia": 1, "frequencia": 1}, "voador": {"relevancia": 1, "frequencia": 1}, "lider": {"relevancia": 1, "frequencia": 1}, "forc": {"relevancia": 1, "frequencia": 3}, "defes": {"relevancia": 1, "frequencia": 1}, "aer": {"relevancia": 1, "frequencia": 3}, "veteran": {"relevancia": 1, "frequencia": 1}, "experient": {"relevancia": 1, "frequencia": 1}, "conhec": {"relevancia": 1, "frequencia": 1}, "serpent": {"relevancia": 1, "frequencia": 3}, "gritant": {"relevancia": 1, "frequencia": 3}, "calm": {"relevancia": 1, "frequencia": 1}, "sob": {"relevancia": 1, "frequencia": 2}, "patrulh": {"relevancia": 1, "frequencia": 1}, "ceus": {"relevancia": 1, "frequencia": 1}, "redor": {"relevancia": 1, "frequencia": 2}, "nov": {"relevancia": 1, "frequencia": 1}, "lar": {"relevancia": 1, "frequencia": 1}, "nunc": {"relevancia": 1, "frequencia": 1}, "problem": {"relevancia": 1, "frequencia": 1}, "boa": {"relevancia": 1, "frequencia": 2}, "pud": {"relevancia": 1, "frequencia": 1}, "resolv": {"relevancia": 1, "frequencia": 1}, "heimerding": {"relevancia": 1, "frequencia": 1}, "companheir": {"relevancia": 1, "frequencia": 1}, "migr": {"relevancia": 1, "frequencia": 1}, "fiz": {"relevancia": 1, "frequencia": 2}, "cienc": {"relevancia": 1, "frequencia": 1}, "torn": {"relevancia": 1, "frequencia": 2}, "estil": {"relevancia": 1, "frequencia": 1}, "vid": {"relevancia": 1, "frequencia": 1}, "imediat": {"relevancia": 1, "frequencia": 1}, "inov": {"relevancia": 1, "frequencia": 1}, "contribuico": {"relevancia": 1, "frequencia": 2}, "comun": {"relevancia": 1, "frequencia": 1}, "tecmaturg": {"relevancia": 1, "frequencia": 1}, "falt": {"relevancia": 1, "frequencia": 2}, "tamanh": {"relevancia": 1, "frequencia": 1}, "compens": {"relevancia": 1, "frequencia": 1}, "trabalh": {"relevancia": 1, "frequencia": 2}, "ganh": {"relevancia": 1, "frequencia": 1}, "titul": {"relevancia": 1, "frequencia": 1}, "ser": {"relevancia": 1, "frequencia": 1}, "test": {"relevancia": 1, "frequencia": 1}, "dess": {"relevancia": 1, "frequencia": 1}, "design": {"relevancia": 1, "frequencia": 1}, "original": {"relevancia": 1, "frequencia": 1}, "helicopter": {"relevancia": 1, "frequencia": 2}, "linh": {"relevancia": 1, "frequencia": 2}, "oper": {"relevancia": 1, "frequencia": 1}, "reconhec": {"relevancia": 1, "frequencia": 1}, "veicul": {"relevancia": 1, "frequencia": 1}, "espinh": {"relevancia": 1, "frequencia": 1}, "dorsal": {"relevancia": 1, "frequencia": 1}, "expedicionar": {"relevancia": 1, "frequencia": 1}, "feb": {"relevancia": 1, "frequencia": 1}, "junt": {"relevancia": 1, "frequencia": 1}, "esquadra": {"relevancia": 1, "frequencia": 1}, "voa": {"relevancia": 1, "frequencia": 1}, "sobr": {"relevancia": 1, "frequencia": 3}, "valoran": {"relevancia": 1, "frequencia": 1}, "faz": {"relevancia": 1, "frequencia": 1}, "levant": {"relevancia": 1, "frequencia": 1}, "topograf": {"relevancia": 1, "frequencia": 1}, "conduz": {"relevancia": 1, "frequencia": 1}, "manobr": {"relevancia": 1, "frequencia": 1}, "acrobat": {"relevancia": 1, "frequencia": 1}, "admir": {"relevancia": 1, "frequencia": 1}, "observ": {"relevancia": 1, "frequencia": 1}, "embaix": {"relevancia": 1, "frequencia": 1}, "renom": {"relevancia": 1, "frequencia": 1}, "mant": {"relevancia": 1, "frequencia": 1}, "control": {"relevancia": 1, "frequencia": 1}, "demonstr": {"relevancia": 1, "frequencia": 1}, "bravur": {"relevancia": 1, "frequencia": 1}, "dem": {"relevancia": 1, "frequencia": 1}, "var": {"relevancia": 1, "frequencia": 2}, "form": {"relevancia": 1, "frequencia": 1}, "quas": {"relevancia": 1, "frequencia": 1}, "sempr": {"relevancia": 1, "frequencia": 1}, "send": {"relevancia": 1, "frequencia": 1}, "voluntari": {"relevancia": 1, "frequencia": 1}, "misso": {"relevancia": 1, "frequencia": 1}, "lev": {"relevancia": 1, "frequencia": 2}, "alem": {"relevancia": 1, "frequencia": 1}, "tant": {"relevancia": 1, "frequencia": 1}, "adquir": {"relevancia": 1, "frequencia": 1}, "inform": {"relevancia": 1, "frequencia": 1}, "confidenc": {"relevancia": 1, "frequencia": 1}, "quant": {"relevancia": 1, "frequencia": 1}, "mensagens": {"relevancia": 1, "frequencia": 1}, "atraves": {"relevancia": 1, "frequencia": 1}, "guerr": {"relevancia": 1, "frequencia": 1}, "triunf": {"relevancia": 1, "frequencia": 1}, "perig": {"relevancia": 1, "frequencia": 1}, "ador": {"relevancia": 1, "frequencia": 1}, "perseguica": {"relevancia": 1, "frequencia": 1}, "manha": {"relevancia": 1, "frequencia": 1}, "apen": {"relevancia": 1, "frequencia": 1}, "primeir": {"relevancia": 1, "frequencia": 1}, "fez": {"relevancia": 1, "frequencia": 1}, "modific": {"relevancia": 1, "frequencia": 1}, "equipando-": {"relevancia": 1, "frequencia": 1}, "arsenal": {"relevancia": 1, "frequencia": 1}, "armas": {"relevancia": 1, "frequencia": 1}, "alguns": {"relevancia": 1, "frequencia": 1}, "acredit": {"relevancia": 1, "frequencia": 1}, "estar": {"relevancia": 1, "frequencia": 1}, "aparec": {"relevancia": 1, "frequencia": 1}, "funcion": {"relevancia": 1, "frequencia": 1}, "apos": {"relevancia": 1, "frequencia": 1}, "cessar-fog": {"relevancia": 1, "frequencia": 1}, "aposent": {"relevancia": 1, "frequencia": 1}, "coment": {"relevancia": 1, "frequencia": 1}, "episodi": {"relevancia": 1, "frequencia": 1}, "gasolin": {"relevancia": 1, "frequencia": 1}, "tanqu": {"relevancia": 1, "frequencia": 1}, "asas": {"relevancia": 1, "frequencia": 1}, "cort": {"relevancia": 1, "frequencia": 1}, "tent": {"relevancia": 1, "frequencia": 1}, "pass": {"relevancia": 1, "frequencia": 1}, "dubl": {"relevancia": 1, "frequencia": 1}, "voo": {"relevancia": 1, "frequencia": 1}, "gui": {"relevancia": 1, "frequencia": 1}, "turist": {"relevancia": 1, "frequencia": 1}, "desfiladeir": {"relevancia": 1, "frequencia": 1}, "mesm": {"relevancia": 1, "frequencia": 1}, "sent": {"relevancia": 1, "frequencia": 1}, "refresc": {"relevancia": 1, "frequencia": 1}, "cheir": {"relevancia": 1, "frequencia": 1}, "polvor": {"relevancia": 1, "frequencia": 1}}